tensorflores/__init__.py
tensorflores/models/__init__.py
tensorflores/models/multilayer_perceptron.py
tensorflores/utils/__init__.py
tensorflores/utils/array_manipulation.py
tensorflores/utils/clustering.py
tensorflores/utils/cpp_generation.py
tensorflores/utils/json_handle.py
tensorflores/utils/quantization.py
tensorflores/utils/autocloud/__init__.py
tensorflores/utils/autocloud/auto_cloud_bias.py
tensorflores/utils/autocloud/auto_cloud_weight.py
tensorflores/utils/autocloud/data_cloud_bias.py
tensorflores/utils/autocloud/data_cloud_weight.py
tensorflores-0.1.11.dist-info/METADATA
tensorflores-0.1.11.dist-info/WHEEL
tensorflores-0.1.11.dist-info/licenses/LICENSE
tensorflores-0.1.11.dist-info/RECORD
