Metadata-Version: 2.4
Name: tensorflores
Version: 0.1.11
Summary: TensorFlores is a Python-based framework for optimizing machine learning deployment in resource-constrained environments, with support for TinyML, EdgeAI, and quantization.
Project-URL: Homepage, https://conect2ai.dca.ufrn.br/
Project-URL: Repository, https://github.com/conect2ai/TensorFlores
Project-URL: Issues, https://github.com/conect2ai/TensorFlores/issues
Author-email: "Thommas K. S. Flores" <thommas.flores.101@ufrn.edu.br>
License: MIT
License-File: LICENSE
Keywords: EdgeAI,Machine Learning,Quantization,TinyML
Classifier: Development Status :: 3 - Alpha
Classifier: Intended Audience :: Developers
Classifier: License :: OSI Approved :: MIT License
Classifier: Operating System :: OS Independent
Classifier: Programming Language :: Python :: 3
Classifier: Programming Language :: Python :: 3.9
Classifier: Topic :: Scientific/Engineering :: Artificial Intelligence
Requires-Python: ==3.9.6
Requires-Dist: numpy==1.26.4
Requires-Dist: pandas==2.2.3
Requires-Dist: river==0.21.2
Requires-Dist: scikit-learn==1.0.2
Requires-Dist: tensorflow==2.15.0
